aws_get_secret/__init__.py
aws_get_secret/get_secret.py
aws_get_secret-1.0.1.dist-info/LICENSE
aws_get_secret-1.0.1.dist-info/METADATA
aws_get_secret-1.0.1.dist-info/WHEEL
aws_get_secret-1.0.1.dist-info/top_level.txt
aws_get_secret-1.0.1.dist-info/RECORD
