Metadata-Version: 2.1
Name: aws-get-secret
Version: 1.0.1
Summary: AWS package which helps your program to retrieve a secret value stored in AWS Secrets Manager.
Home-page: https://github.com/idenfy/AwsGetSecret.git
Author: Deividas Tamkus, Laimonas Sutkus
Author-email: dtamkus@gmail.com (deividas@idenfy.com), laimonas.sutkus@gmail.com (laimonas@idenfy.com)
License: GNU GENERAL PUBLIC LICENSE Version 3
Keywords: AWS SecretsManager Secret
Platform: UNKNOWN
Classifier: Programming Language :: Python :: 3
Classifier: Operating System :: OS Independent
Requires-Dist: boto3
